CHATB0Tv2/__init__.py
CHATB0Tv2-1.0.dist-info/METADATA
CHATB0Tv2-1.0.dist-info/WHEEL
CHATB0Tv2-1.0.dist-info/top_level.txt
CHATB0Tv2-1.0.dist-info/RECORD
